{"nodes": [{"id": "get_current_user", "label": "get-current-user.ts", "file_type": "code", "source_file": "lib/get-current-user.ts", "source_location": "L1"}, {"id": "get_current_user_getcurrentuser", "label": "getCurrentUser()", "file_type": "code", "source_file": "lib/get-current-user.ts", "source_location": "L8"}], "edges": [{"source": "get_current_user", "target": "client", "relation": "imports_from", "confidence": "EXTRACTED", "source_file": "lib/get-current-user.ts", "source_location": "L2", "weight": 1.0}, {"source": "get_current_user", "target": "get_current_user_getcurrentuser", "relation": "contains", "confidence": "EXTRACTED", "source_file": "lib/get-current-user.ts", "source_location": "L8", "weight": 1.0}]}