{"nodes": [{"id": "page", "label": "page.tsx", "file_type": "code", "source_file": "app/dashboard/page.tsx", "source_location": "L1"}, {"id": "page_parsegroupdate", "label": "parseGroupDate()", "file_type": "code", "source_file": "app/dashboard/page.tsx", "source_location": "L9"}, {"id": "page_getgroupsinrange", "label": "getGroupsInRange()", "file_type": "code", "source_file": "app/dashboard/page.tsx", "source_location": "L15"}, {"id": "page_dashboardskeleton", "label": "DashboardSkeleton()", "file_type": "code", "source_file": "app/dashboard/page.tsx", "source_location": "L21"}], "edges": [{"source": "page", "target": "link", "relation": "imports_from", "confidence": "EXTRACTED", "source_file": "app/dashboard/page.tsx", "source_location": "L3", "weight": 1.0}, {"source": "page", "target": "use_dashboard", "relation": "imports_from", "confidence": "EXTRACTED", "source_file": "app/dashboard/page.tsx", "source_location": "L4", "weight": 1.0}, {"source": "page", "target": "overview_widget", "relation": "imports_from", "confidence": "EXTRACTED", "source_file": "app/dashboard/page.tsx", "source_location": "L5", "weight": 1.0}, {"source": "page", "target": "lucide_react", "relation": "imports_from", "confidence": "EXTRACTED", "source_file": "app/dashboard/page.tsx", "source_location": "L6", "weight": 1.0}, {"source": "page", "target": "react", "relation": "imports_from", "confidence": "EXTRACTED", "source_file": "app/dashboard/page.tsx", "source_location": "L7", "weight": 1.0}, {"source": "page", "target": "page_parsegroupdate", "relation": "contains", "confidence": "EXTRACTED", "source_file": "app/dashboard/page.tsx", "source_location": "L9", "weight": 1.0}, {"source": "page", "target": "page_getgroupsinrange", "relation": "contains", "confidence": "EXTRACTED", "source_file": "app/dashboard/page.tsx", "source_location": "L15", "weight": 1.0}, {"source": "page", "target": "page_dashboardskeleton", "relation": "contains", "confidence": "EXTRACTED", "source_file": "app/dashboard/page.tsx", "source_location": "L21", "weight": 1.0}]}